Metadata-Version: 2.4
Name: soprano-sdk
Version: 0.2.7
Summary: YAML-driven workflow engine with AI agent integration for building conversational SOPs
Author: Arvind Thangamani
License: MIT
License-File: LICENSE
Keywords: agent,ai,conversational,langgraph,sop,soprano,workflow
Classifier: Development Status :: 3 - Alpha
Classifier: Intended Audience :: Developers
Classifier: License :: OSI Approved :: MIT License
Classifier: Programming Language :: Python :: 3
Classifier: Programming Language :: Python :: 3.12
Requires-Python: >=3.12
Requires-Dist: agno>=2.0.7
Requires-Dist: crewai>=0.186.1
Requires-Dist: jsonschema>=4.0.0
Requires-Dist: langchain-community>=0.4.1
Requires-Dist: langchain-core>=0.3.67
Requires-Dist: langchain-openai>=1.0.3
Requires-Dist: langchain>=1.0.7
Requires-Dist: langfuse>=3.10.1
Requires-Dist: langgraph==1.0.2
Requires-Dist: openai>=1.92.1
Requires-Dist: pydantic-ai>=1.22.0
Requires-Dist: pydantic>=2.0.0
Requires-Dist: pytest>=9.0.1
Requires-Dist: pyyaml>=6.0
Provides-Extra: dev
Requires-Dist: gradio>=5.46.0; extra == 'dev'
Requires-Dist: pytest>=7.0.0; extra == 'dev'
Provides-Extra: persistence
Requires-Dist: langgraph-checkpoint-mongodb>=0.2.0; extra == 'persistence'
Requires-Dist: pymongo>=4.0.0; extra == 'persistence'
Provides-Extra: supervisors
Requires-Dist: crewai>=0.1.0; extra == 'supervisors'
Requires-Dist: langchain-openai>=0.3.34; extra == 'supervisors'
